Workbook

Sheet Instrucciones
A1: INSTRUMENTOS DE MONITOREO, FIDELIDAD Y CONTROL DE INCIDENCIAS
A2: Universidad de Huánuco – Ingeniería de Sistemas e Informática – Seminario de Tesis III (2026-II) – MBA Jenny Reynoso Palpa
B4: DATOS GENERALES DEL TESISTA
B5: Apellidos y nombres | C5: Trujillo Avila, Marcel Alexander Javier; Godoy Condezo, Alejandro Jeanpier
B6: Código de estudiante
B7: Título de la tesis | C7: Influencia de una aplicación web móvil con asistente conversacional inteligente en la experiencia de usuario de lectores de Tu Diario Huánuco, 2026
B8: Variable independiente (VI) | C8: Aplicación web con asistente conversacional
B9: Variable dependiente (VD) | C9: Experiencia de lectores
B10: Diseño | C10: Preexperimental: G O1 X O2
B11: Tamaño de muestra (n) | C11: 108
B12: Inicio de la intervención | C12: 46313
B13: Fin de la intervención | C13: 46353
B14: Asesor(a) | C14: Mg. …
B16: CONTENIDO DEL LIBRO
B17: Hoja | C17: Uso / instrumento del sílabo
B18: 1_Ficha_Monitoreo | C18: Ficha de monitoreo semanal: programado vs. ejecutado e Índice de Fidelidad (IF) semanal.
B19: 2_Registro_Incidencias | C19: Registro de incidencias: código, tipo, impacto, urgencia, severidad automática, acción y estado.
B20: 3_Cotejo_Fidelidad | C20: Lista de cotejo de fidelidad por dimensión: IF global y nivel (alta, moderada, baja).
B21: 4_Matriz_Variables | C21: Matriz de variables intervinientes: riesgo, estrategia de control y evidencia.
B22: 5_Desviaciones | C22: Comparación planificado vs. real con clasificación automática de la desviación.
B23: 6_Control_Cambios | C23: Registro de control de cambios aprobados por el asesor.
B24: 7_Rubrica | C24: Rúbrica del informe de seguimiento (autoevaluación y evaluación docente).
B25: 8_Resumen | C25: Tablero resumen con indicadores y gráficos para el informe de seguimiento.
B26: Listas | C26: Listas desplegables y matriz de prioridad (no modificar).
B28: LEYENDA Y REGLAS
B29: Texto azul / fondo amarillo | C29: Celda de ingreso de datos (el tesista la llena).
B30: Texto negro / fondo blanco | C30: Fórmula automática: no la sobrescriba.
B31: • Los datos precargados son un CASO DE EJEMPLO: reemplácelos por los de su intervención.
B32: • Registre las incidencias el mismo día en que ocurren, con código correlativo INC-001, INC-002, …
B33: • Umbral de alta fidelidad: IF ≥ 80 % (Borrelli et al., 2005); 60–79 % moderada; < 60 % baja.
B34: • Cada código (FM, INC, CC) debe coincidir con la evidencia adjunta en el portafolio (trazabilidad).
B35: • Adjunte este libro como anexo del informe de seguimiento y, luego, del informe final de tesis.

Sheet 1_Ficha_Monitoreo
A1: INSTRUMENTO 1: FICHA DE MONITOREO SEMANAL
A2: Seminario de Tesis III – Sesión 6: Monitoreo, fidelidad y control de incidencias | Celdas amarillas con texto azul = datos que ingresa el tesista; celdas blancas = fórmulas (no modificar)
A3: Metas del protocolo (editables): | D3: Disponibilidad ≥ | E3: 0.95 | F3: Participación ≥ | G3: 0.8 | H3: Exposición ≥ | I3: 0.8 | J3: Soporte atendido ≥ | K3: 1
A5: Código FM | B5: Semana | C5: Fecha inicio | D5: Fecha fin | E5: Horas programadas | F5: Horas operativas | G5: % Disponibilidad | H5: Participantes previstos | I5: Participantes activos | J5: % Participación | K5: Transacciones programadas | L5: Transacciones reales | M5: % Exposición | N5: Solicitudes de soporte | O5: Soportes atendidos | P5: Uso del GC detectado (Sí/No) | Q5: IF semanal | R5: Nivel | S5: Incidencias / observaciones
A6: FM-01 | B6: S1 | C6: 46313 | D6: =IF(C6="","",C6+6) -> 46319 | G6: =IF(OR(E6="",E6=0),"",F6/E6) | H6: 108 | J6: =IF(OR(H6="",H6=0),"",I6/H6) -> 0 | M6: =IF(OR(K6="",K6=0),"",L6/K6) | Q6: =IF(E6="","",((G6>=$E$3)+(J6>=$G$3)+(M6>=$I$3)+(IF(N6=0,1,O6/N6)>=$K$3)+(P6="No"))/5) | R6: =IF(Q6="","",IF(Q6>=0.8,"Alta",IF(Q6>=0.6,"Moderada","Baja")))
A7: FM-02 | B7: S2 | C7: 46320 | D7: =IF(C7="","",C7+6) -> 46326 | G7: =IF(OR(E7="",E7=0),"",F7/E7) | H7: 108 | J7: =IF(OR(H7="",H7=0),"",I7/H7) -> 0 | M7: =IF(OR(K7="",K7=0),"",L7/K7) | Q7: =IF(E7="","",((G7>=$E$3)+(J7>=$G$3)+(M7>=$I$3)+(IF(N7=0,1,O7/N7)>=$K$3)+(P7="No"))/5) | R7: =IF(Q7="","",IF(Q7>=0.8,"Alta",IF(Q7>=0.6,"Moderada","Baja")))
A8: FM-03 | B8: S3 | C8: 46327 | D8: =IF(C8="","",C8+6) -> 46333 | G8: =IF(OR(E8="",E8=0),"",F8/E8) | H8: 108 | J8: =IF(OR(H8="",H8=0),"",I8/H8) -> 0 | M8: =IF(OR(K8="",K8=0),"",L8/K8) | Q8: =IF(E8="","",((G8>=$E$3)+(J8>=$G$3)+(M8>=$I$3)+(IF(N8=0,1,O8/N8)>=$K$3)+(P8="No"))/5) | R8: =IF(Q8="","",IF(Q8>=0.8,"Alta",IF(Q8>=0.6,"Moderada","Baja")))
A9: FM-04 | B9: S4 | C9: 46334 | D9: =IF(C9="","",C9+6) -> 46340 | G9: =IF(OR(E9="",E9=0),"",F9/E9) | H9: 108 | J9: =IF(OR(H9="",H9=0),"",I9/H9) -> 0 | M9: =IF(OR(K9="",K9=0),"",L9/K9) | Q9: =IF(E9="","",((G9>=$E$3)+(J9>=$G$3)+(M9>=$I$3)+(IF(N9=0,1,O9/N9)>=$K$3)+(P9="No"))/5) | R9: =IF(Q9="","",IF(Q9>=0.8,"Alta",IF(Q9>=0.6,"Moderada","Baja")))
A10: FM-05 | B10: S5 | C10: 46341 | D10: =IF(C10="","",C10+6) -> 46347 | G10: =IF(OR(E10="",E10=0),"",F10/E10) | H10: 108 | J10: =IF(OR(H10="",H10=0),"",I10/H10) -> 0 | M10: =IF(OR(K10="",K10=0),"",L10/K10) | Q10: =IF(E10="","",((G10>=$E$3)+(J10>=$G$3)+(M10>=$I$3)+(IF(N10=0,1,O10/N10)>=$K$3)+(P10="No"))/5) | R10: =IF(Q10="","",IF(Q10>=0.8,"Alta",IF(Q10>=0.6,"Moderada","Baja")))
A11: FM-06 | B11: S6 | C11: 46348 | D11: =IF(C11="","",C11+6) -> 46354 | G11: =IF(OR(E11="",E11=0),"",F11/E11) | H11: 108 | J11: =IF(OR(H11="",H11=0),"",I11/H11) -> 0 | M11: =IF(OR(K11="",K11=0),"",L11/K11) | Q11: =IF(E11="","",((G11>=$E$3)+(J11>=$G$3)+(M11>=$I$3)+(IF(N11=0,1,O11/N11)>=$K$3)+(P11="No"))/5) | R11: =IF(Q11="","",IF(Q11>=0.8,"Alta",IF(Q11>=0.6,"Moderada","Baja")))
A12: FM-07 | B12: S7 | D12: =IF(C12="","",C12+6) | G12: =IF(OR(E12="",E12=0),"",F12/E12) | J12: =IF(OR(H12="",H12=0),"",I12/H12) | M12: =IF(OR(K12="",K12=0),"",L12/K12) | Q12: =IF(E12="","",((G12>=$E$3)+(J12>=$G$3)+(M12>=$I$3)+(IF(N12=0,1,O12/N12)>=$K$3)+(P12="No"))/5) | R12: =IF(Q12="","",IF(Q12>=0.8,"Alta",IF(Q12>=0.6,"Moderada","Baja")))
A13: FM-08 | B13: S8 | D13: =IF(C13="","",C13+6) | G13: =IF(OR(E13="",E13=0),"",F13/E13) | J13: =IF(OR(H13="",H13=0),"",I13/H13) | M13: =IF(OR(K13="",K13=0),"",L13/K13) | Q13: =IF(E13="","",((G13>=$E$3)+(J13>=$G$3)+(M13>=$I$3)+(IF(N13=0,1,O13/N13)>=$K$3)+(P13="No"))/5) | R13: =IF(Q13="","",IF(Q13>=0.8,"Alta",IF(Q13>=0.6,"Moderada","Baja")))
A14: FM-09 | B14: S9 | D14: =IF(C14="","",C14+6) | G14: =IF(OR(E14="",E14=0),"",F14/E14) | J14: =IF(OR(H14="",H14=0),"",I14/H14) | M14: =IF(OR(K14="",K14=0),"",L14/K14) | Q14: =IF(E14="","",((G14>=$E$3)+(J14>=$G$3)+(M14>=$I$3)+(IF(N14=0,1,O14/N14)>=$K$3)+(P14="No"))/5) | R14: =IF(Q14="","",IF(Q14>=0.8,"Alta",IF(Q14>=0.6,"Moderada","Baja")))
A15: FM-10 | B15: S10 | D15: =IF(C15="","",C15+6) | G15: =IF(OR(E15="",E15=0),"",F15/E15) | J15: =IF(OR(H15="",H15=0),"",I15/H15) | M15: =IF(OR(K15="",K15=0),"",L15/K15) | Q15: =IF(E15="","",((G15>=$E$3)+(J15>=$G$3)+(M15>=$I$3)+(IF(N15=0,1,O15/N15)>=$K$3)+(P15="No"))/5) | R15: =IF(Q15="","",IF(Q15>=0.8,"Alta",IF(Q15>=0.6,"Moderada","Baja")))
A16: FM-11 | B16: S11 | D16: =IF(C16="","",C16+6) | G16: =IF(OR(E16="",E16=0),"",F16/E16) | J16: =IF(OR(H16="",H16=0),"",I16/H16) | M16: =IF(OR(K16="",K16=0),"",L16/K16) | Q16: =IF(E16="","",((G16>=$E$3)+(J16>=$G$3)+(M16>=$I$3)+(IF(N16=0,1,O16/N16)>=$K$3)+(P16="No"))/5) | R16: =IF(Q16="","",IF(Q16>=0.8,"Alta",IF(Q16>=0.6,"Moderada","Baja")))
A17: FM-12 | B17: S12 | D17: =IF(C17="","",C17+6) | G17: =IF(OR(E17="",E17=0),"",F17/E17) | J17: =IF(OR(H17="",H17=0),"",I17/H17) | M17: =IF(OR(K17="",K17=0),"",L17/K17) | Q17: =IF(E17="","",((G17>=$E$3)+(J17>=$G$3)+(M17>=$I$3)+(IF(N17=0,1,O17/N17)>=$K$3)+(P17="No"))/5) | R17: =IF(Q17="","",IF(Q17>=0.8,"Alta",IF(Q17>=0.6,"Moderada","Baja")))
A18: TOTAL / PROMEDIO | E18: =SUM(E6:E17) -> 0 | F18: =SUM(F6:F17) -> 0 | G18: =IF(E18=0,"",F18/E18) | H18: =AVERAGE(H6:H17) -> 108 | I18: =AVERAGE(I6:I17) -> #DIV/0! | J18: =IFERROR(I18/H18,"") | K18: =SUM(K6:K17) -> 0 | L18: =SUM(L6:L17) -> 0 | M18: =IF(K18=0,"",L18/K18) | N18: =SUM(N6:N17) -> 0 | O18: =SUM(O6:O17) -> 0 | P18: =COUNTIF(P6:P17,"Sí")&" sem. con uso GC" -> 0 sem. con uso GC | Q18: =IFERROR(AVERAGE(Q6:Q17),"") | R18: =IF(Q18="","",IF(Q18>=0.8,"Alta",IF(Q18>=0.6,"Moderada","Baja"))) | S18: IF semanal = criterios cumplidos ÷ 5 (disponibilidad, participación, exposición, soporte, sin contaminación del GC)

Sheet 2_Registro_Incidencias
A1: INSTRUMENTO 2: REGISTRO DE INCIDENCIAS
A2: Seminario de Tesis III – Sesión 6: Monitoreo, fidelidad y control de incidencias | Celdas amarillas con texto azul = datos que ingresa el tesista; celdas blancas = fórmulas (no modificar)
A3: La severidad se calcula con la matriz impacto × urgencia (hoja Listas). Describa hechos observables, no opiniones.
A4: Código | B4: Fecha | C4: Hora | D4: Semana | E4: Grupo | F4: Descripción objetiva (hechos) | G4: Tipo | H4: Impacto | I4: Urgencia | J4: Severidad (auto) | K4: Amenaza a la validez | L4: Causa raíz (5 porqués / Ishikawa) | M4: Acción correctiva | N4: Responsable | O4: Plazo | P4: Fecha de cierre | Q4: Estado | R4: Días de resolución | S4: Evidencia (código / archivo)
J5: {=IFERROR(INDEX(Listas!$L$3:$N$5,MATCH(H5,Listas!$K$3:$K$5,0),MATCH(I5,Listas!$L$2:$N$2,0)),"")} | R5: =IF(OR(B5="",P5=""),"",P5-B5)
J6: {=IFERROR(INDEX(Listas!$L$3:$N$5,MATCH(H6,Listas!$K$3:$K$5,0),MATCH(I6,Listas!$L$2:$N$2,0)),"")} | R6: =IF(OR(B6="",P6=""),"",P6-B6)
J7: {=IFERROR(INDEX(Listas!$L$3:$N$5,MATCH(H7,Listas!$K$3:$K$5,0),MATCH(I7,Listas!$L$2:$N$2,0)),"")} | R7: =IF(OR(B7="",P7=""),"",P7-B7)
J8: {=IFERROR(INDEX(Listas!$L$3:$N$5,MATCH(H8,Listas!$K$3:$K$5,0),MATCH(I8,Listas!$L$2:$N$2,0)),"")} | R8: =IF(OR(B8="",P8=""),"",P8-B8)
A9: =IF(B9="","","INC-"&TEXT(ROW()-1,"000")) | J9: {=IFERROR(INDEX(Listas!$L$3:$N$5,MATCH(H9,Listas!$K$3:$K$5,0),MATCH(I9,Listas!$L$2:$N$2,0)),"")} | R9: =IF(OR(B9="",P9=""),"",P9-B9)
A10: =IF(B10="","","INC-"&TEXT(ROW()-1,"000")) | J10: {=IFERROR(INDEX(Listas!$L$3:$N$5,MATCH(H10,Listas!$K$3:$K$5,0),MATCH(I10,Listas!$L$2:$N$2,0)),"")} | R10: =IF(OR(B10="",P10=""),"",P10-B10)
A11: =IF(B11="","","INC-"&TEXT(ROW()-1,"000")) | J11: {=IFERROR(INDEX(Listas!$L$3:$N$5,MATCH(H11,Listas!$K$3:$K$5,0),MATCH(I11,Listas!$L$2:$N$2,0)),"")} | R11: =IF(OR(B11="",P11=""),"",P11-B11)
A12: =IF(B12="","","INC-"&TEXT(ROW()-1,"000")) | J12: {=IFERROR(INDEX(Listas!$L$3:$N$5,MATCH(H12,Listas!$K$3:$K$5,0),MATCH(I12,Listas!$L$2:$N$2,0)),"")} | R12: =IF(OR(B12="",P12=""),"",P12-B12)
A13: =IF(B13="","","INC-"&TEXT(ROW()-1,"000")) | J13: {=IFERROR(INDEX(Listas!$L$3:$N$5,MATCH(H13,Listas!$K$3:$K$5,0),MATCH(I13,Listas!$L$2:$N$2,0)),"")} | R13: =IF(OR(B13="",P13=""),"",P13-B13)
A14: =IF(B14="","","INC-"&TEXT(ROW()-1,"000")) | J14: {=IFERROR(INDEX(Listas!$L$3:$N$5,MATCH(H14,Listas!$K$3:$K$5,0),MATCH(I14,Listas!$L$2:$N$2,0)),"")} | R14: =IF(OR(B14="",P14=""),"",P14-B14)
A15: =IF(B15="","","INC-"&TEXT(ROW()-1,"000")) | J15: {=IFERROR(INDEX(Listas!$L$3:$N$5,MATCH(H15,Listas!$K$3:$K$5,0),MATCH(I15,Listas!$L$2:$N$2,0)),"")} | R15: =IF(OR(B15="",P15=""),"",P15-B15)
A16: =IF(B16="","","INC-"&TEXT(ROW()-1,"000")) | J16: {=IFERROR(INDEX(Listas!$L$3:$N$5,MATCH(H16,Listas!$K$3:$K$5,0),MATCH(I16,Listas!$L$2:$N$2,0)),"")} | R16: =IF(OR(B16="",P16=""),"",P16-B16)
A17: =IF(B17="","","INC-"&TEXT(ROW()-1,"000")) | J17: {=IFERROR(INDEX(Listas!$L$3:$N$5,MATCH(H17,Listas!$K$3:$K$5,0),MATCH(I17,Listas!$L$2:$N$2,0)),"")} | R17: =IF(OR(B17="",P17=""),"",P17-B17)
A18: =IF(B18="","","INC-"&TEXT(ROW()-1,"000")) | J18: {=IFERROR(INDEX(Listas!$L$3:$N$5,MATCH(H18,Listas!$K$3:$K$5,0),MATCH(I18,Listas!$L$2:$N$2,0)),"")} | R18: =IF(OR(B18="",P18=""),"",P18-B18)
A19: =IF(B19="","","INC-"&TEXT(ROW()-1,"000")) | J19: {=IFERROR(INDEX(Listas!$L$3:$N$5,MATCH(H19,Listas!$K$3:$K$5,0),MATCH(I19,Listas!$L$2:$N$2,0)),"")} | R19: =IF(OR(B19="",P19=""),"",P19-B19)
A20: =IF(B20="","","INC-"&TEXT(ROW()-1,"000")) | J20: {=IFERROR(INDEX(Listas!$L$3:$N$5,MATCH(H20,Listas!$K$3:$K$5,0),MATCH(I20,Listas!$L$2:$N$2,0)),"")} | R20: =IF(OR(B20="",P20=""),"",P20-B20)
... A34: =IF(B34="","","INC-"&TEXT(ROW()-1,"000")) | J34: {=IFERROR(INDEX(Listas!$L$3:$N$5,MATCH(H34,Listas!$K$3:$K$5,0),MATCH(I34,Listas!$L$2:$N$2,0)),"")} | R34: =IF(OR(B34="",P34=""),"",P34-B34)

Sheet 3_Cotejo_Fidelidad
A1: INSTRUMENTO 3: LISTA DE COTEJO DE FIDELIDAD
A2: Seminario de Tesis III – Sesión 6: Monitoreo, fidelidad y control de incidencias | Celdas amarillas con texto azul = datos que ingresa el tesista; celdas blancas = fórmulas (no modificar)
A4: N.° | B4: Dimensión | C4: Criterio de fidelidad | D4: ¿Cumple? (Sí/No) | E4: Evidencia | F4: Observación
A5: 1 | B5: Adherencia | C5: La intervención se ejecutó durante el periodo programado | E5: Cronograma de campo y FM-01 a FM-06
A6: 2 | B6: Exposición | C6: Se cumplió la frecuencia de uso establecida | E6: FM-01 a FM-06
A7: 3 | B7: Adherencia | C7: Se usaron todos los módulos definidos en el protocolo | E7: Logs de auditoría
A8: 4 | B8: Calidad | C8: Todos los participantes recibieron la misma capacitación | E8: Lista de asistencia
A9: 5 | B9: Calidad | C9: El sistema tuvo una disponibilidad ≥ 95 % | E9: Hoja 1: % disponibilidad
A10: 6 | B10: Respuesta | C10: ≥ 80 % de los participantes usaron la solución | E10: Hoja 1: % participación
A11: 7 | B11: Diferenciación | C11: El grupo de comparación no accedió a la solución | E11: Logs de acceso | F11: No aplica: diseño preexperimental de grupo único, sin grupo de comparación (PDT §3.3)
A12: 8 | B12: Calidad | C12: Toda incidencia fue registrada, clasificada y atendida | E12: Hoja 2
A13: 9 | B13: Adherencia | C13: Los cambios cuentan con aprobación documentada | E13: Hoja 6: control de cambios
A14: 10 | B14: Calidad | C14: Existen evidencias trazables (logs, actas, capturas) | E14: Portafolio de evidencias
B16: Criterios cumplidos | C16: =COUNTIF(D5:D14,"Sí") -> 0 | E16: Dimensión | F16: IF por dimensión
B17: Criterios aplicables | C17: =COUNTA(D5:D14) -> 0 | E17: Adherencia | F17: =IF(COUNTIF($B$5:$B$14,E17)=0,"",COUNTIFS($B$5:$B$14,E17,$D$5:$D$14,"Sí")/COUNTIF($B$5:$B$14,E17)) -> 0
B18: IF global | C18: =IF(C17=0,"",C16/C17) | E18: Exposición | F18: =IF(COUNTIF($B$5:$B$14,E18)=0,"",COUNTIFS($B$5:$B$14,E18,$D$5:$D$14,"Sí")/COUNTIF($B$5:$B$14,E18)) -> 0
B19: Nivel de fidelidad | C19: =IF(C18="","",IF(C18>=0.8,"Alta",IF(C18>=0.6,"Moderada","Baja"))) | E19: Calidad | F19: =IF(COUNTIF($B$5:$B$14,E19)=0,"",COUNTIFS($B$5:$B$14,E19,$D$5:$D$14,"Sí")/COUNTIF($B$5:$B$14,E19)) -> 0
B20: Interpretación | C20: =IF(C19="Alta","Fidelidad aceptable: el efecto puede atribuirse a la solución.",IF(C19="Moderada","Aplicar acciones correctivas antes del postest.","Compromete la validez interna: reportar en limitaciones.")) -> Compromete la validez interna: reportar en limitaciones. | E20: Respuesta | F20: =IF(COUNTIF($B$5:$B$14,E20)=0,"",COUNTIFS($B$5:$B$14,E20,$D$5:$D$14,"Sí")/COUNTIF($B$5:$B$14,E20)) -> 0
E21: Diferenciación | F21: =IF(COUNTIF($B$5:$B$14,E21)=0,"",COUNTIFS($B$5:$B$14,E21,$D$5:$D$14,"Sí")/COUNTIF($B$5:$B$14,E21)) -> 0
A23: Umbral de alta fidelidad: ≥ 80 % (Borrelli et al., 2005). Dimensiones según Dane y Schneider (1998) y Carroll et al. (2007).

Sheet 4_Matriz_Variables
A1: INSTRUMENTO 4: MATRIZ DE VARIABLES INTERVINIENTES
A2: Seminario de Tesis III – Sesión 6: Monitoreo, fidelidad y control de incidencias | Celdas amarillas con texto azul = datos que ingresa el tesista; celdas blancas = fórmulas (no modificar)
A4: N.° | B4: Variable interviniente | C4: Tipo | D4: Posible efecto sobre la VD | E4: Probabilidad (1–3) | F4: Impacto (1–3) | G4: Nivel de riesgo (auto) | H4: Estrategia de control | I4: Evidencia | J4: Estado de control | K4: Amenaza asociada
A5: 1 | B5: Conectividad móvil (3G/4G/5G) | C5: Tecnológica | D5: La latencia y los cortes de red alteran el tiempo de búsqueda percibido en el postest | E5: 3 | F5: 2 | G5: =IF(OR(E5="",F5=""),"",IF(E5*F5>=6,"Alto",IF(E5*F5>=3,"Medio","Bajo"))) -> Alto | H5: Registrar por separado la latencia del servidor y el tiempo de red percibido por el navegador | I5: Logs de telemetría del sistema | J5: Parcialmente controlada | K5: Instrumentación
A6: 2 | B6: Sesgo de selección por afinidad digital | C6: Del participante | D6: Lectores jóvenes con mayor afinidad digital podrían mejorar más rápido que el resto | E6: 2 | F6: 2 | G6: =IF(OR(E6="",F6=""),"",IF(E6*F6>=6,"Alto",IF(E6*F6>=3,"Medio","Bajo"))) -> Medio | H6: Diversificar canales de invitación (diario impreso y banners rotativos) y caracterizar demográficamente la muestra | I6: Ficha de perfil demográfico | J6: Parcialmente controlada | K6: Selección
A7: 3 | B7: Experiencia previa con asistentes conversacionales | C7: Del participante | D7: Usuarios con más práctica usan el chat con mayor rapidez y puntúan mejor la usabilidad | E7: 2 | F7: 2 | G7: =IF(OR(E7="",F7=""),"",IF(E7*F7>=6,"Alto",IF(E7*F7>=3,"Medio","Bajo"))) -> Medio | H7: Registrar el nivel de experiencia previa en la ficha de perfil y considerarlo en el análisis | I7: Ficha de perfil | J7: Controlada | K7: Selección
A8: 4 | B8: Eventos coyunturales locales | C8: Externa / temporal | D8: Eventos locales atípicos elevan el interés por las noticias y alteran la motivación del lector | E8: 2 | F8: 3 | G8: =IF(OR(E8="",F8=""),"",IF(E8*F8>=6,"Alto",IF(E8*F8>=3,"Medio","Bajo"))) -> Alto | H8: Estandarizar las tareas de búsqueda y evitar aplicar las pruebas en periodos de alta volatilidad social o política | I8: Bitácora de eventos locales | J8: Parcialmente controlada | K8: Historia
A9: 5 | B9: Efecto clic cero (zero-click) | C9: Tecnológica | D9: Las respuestas resumidas reducen la navegación a los artículos y pueden sesgar la satisfacción | E9: 2 | F9: 2 | G9: =IF(OR(E9="",F9=""),"",IF(E9*F9>=6,"Alto",IF(E9*F9>=3,"Medio","Bajo"))) -> Medio | H9: Hipervínculos inline obligatorios en cada cita y acordeón de fuentes en la interfaz | I9: Logs de clics hacia los artículos fuente | J9: Controlada | K9: Instrumentación
A10: 6 | B10: Cuotas gratuitas (free tier) de APIs y base de datos | C10: Tecnológica | D10: Los límites de consumo pueden degradar o interrumpir el asistente durante la exposición | E10: 2 | F10: 3 | G10: =IF(OR(E10="",F10=""),"",IF(E10*F10>=6,"Alto",IF(E10*F10>=3,"Medio","Bajo"))) -> Alto | H10: Caché de vectores y de peticiones; limitar las consultas repetitivas al modelo de lenguaje | I10: Logs de disponibilidad y consumo de API | J10: Parcialmente controlada | K10: Dosis baja (fidelidad)
A11: 7 | B11: Doble rol del investigador (desarrollador del diario) | C11: Del investigador | D11: Posible sesgo al asistir a los participantes o al registrar las mediciones | E11: 1 | F11: 2 | G11: =IF(OR(E11="",F11=""),"",IF(E11*F11>=6,"Alto",IF(E11*F11>=3,"Medio","Bajo"))) -> Bajo | H11: Medición automática con logs y tareas de búsqueda estandarizadas, sin intervención del investigador | I11: Ficha de registro de tiempos y clics (telemetría) | J11: Controlada | K11: Instrumentación
A12: 8 | B12: Abandono de participantes (pretest o postest incompleto) | C12: Del participante | D12: La pérdida de casos reduce el tamaño de muestra y la potencia del contraste | E12: 2 | F12: 2 | G12: =IF(OR(E12="",F12=""),"",IF(E12*F12>=6,"Alto",IF(E12*F12>=3,"Medio","Bajo"))) -> Medio | H12: Seguimiento de participantes y reemplazo hasta completar la cuota de 108 con instrumentos completos | I12: Registro de participantes | J12: Parcialmente controlada | K12: Mortalidad experimental
A13: 9 | G13: =IF(OR(E13="",F13=""),"",IF(E13*F13>=6,"Alto",IF(E13*F13>=3,"Medio","Bajo")))
A14: 10 | G14: =IF(OR(E14="",F14=""),"",IF(E14*F14>=6,"Alto",IF(E14*F14>=3,"Medio","Bajo")))
A15: 11 | G15: =IF(OR(E15="",F15=""),"",IF(E15*F15>=6,"Alto",IF(E15*F15>=3,"Medio","Bajo")))
A16: 12 | G16: =IF(OR(E16="",F16=""),"",IF(E16*F16>=6,"Alto",IF(E16*F16>=3,"Medio","Bajo")))
A18: Nivel de riesgo = Probabilidad × Impacto: ≥ 6 Alto; 3–5 Medio; 1–2 Bajo. Toda variable debe tener una estrategia de control y una evidencia verificable.

Sheet 5_Desviaciones
A1: COMPARACIÓN PLANIFICADO VS. REAL (DESVIACIONES DEL PROTOCOLO)
A2: Seminario de Tesis III – Sesión 6: Monitoreo, fidelidad y control de incidencias | Celdas amarillas con texto azul = datos que ingresa el tesista; celdas blancas = fórmulas (no modificar)
A3: Regla: la desviación es MAYOR si afecta la dosis, a los participantes o la medición de la VD; si no, es MENOR.
A5: N.° | B5: Elemento del protocolo | C5: Planificado | D5: Real | E5: Unidad | F5: Desviación (%) | G5: ¿Afecta dosis, participantes o medición? | H5: Tipo (auto) | I5: Acción correctiva / justificación | J5: Evidencia
A6: 1 | B6: Duración de la intervención (18/10 al 27/11/2026) | C6: 6 | E6: semanas | F6: =IF(OR(C6="",D6="",C6=0),"",(D6-C6)/C6) | H6: =IF(F6="","",IF(F6=0,"Sin desviación",IF(G6="Sí","Mayor","Menor")))
A7: 2 | B7: Tamaño de muestra con pretest y postest completos | C7: 108 | E7: lectores | F7: =IF(OR(C7="",D7="",C7=0),"",(D7-C7)/C7) | H7: =IF(F7="","",IF(F7=0,"Sin desviación",IF(G7="Sí","Mayor","Menor")))
A8: 3 | B8: Tareas de búsqueda por participante | C8: 2 | E8: tareas | F8: =IF(OR(C8="",D8="",C8=0),"",(D8-C8)/C8) | H8: =IF(F8="","",IF(F8=0,"Sin desviación",IF(G8="Sí","Mayor","Menor")))
A9: 4 | B9: Tiempo máximo por tarea de búsqueda | C9: 300 | E9: segundos | F9: =IF(OR(C9="",D9="",C9=0),"",(D9-C9)/C9) | H9: =IF(F9="","",IF(F9=0,"Sin desviación",IF(G9="Sí","Mayor","Menor")))
A10: 5 | B10: Ventana de aplicación del postest (28/11 al 05/12/2026) | C10: 8 | E10: días | F10: =IF(OR(C10="",D10="",C10=0),"",(D10-C10)/C10) | H10: =IF(F10="","",IF(F10=0,"Sin desviación",IF(G10="Sí","Mayor","Menor")))
A11: 6 | F11: =IF(OR(C11="",D11="",C11=0),"",(D11-C11)/C11) | H11: =IF(F11="","",IF(F11=0,"Sin desviación",IF(G11="Sí","Mayor","Menor")))
A12: 7 | F12: =IF(OR(C12="",D12="",C12=0),"",(D12-C12)/C12) | H12: =IF(F12="","",IF(F12=0,"Sin desviación",IF(G12="Sí","Mayor","Menor")))
A13: 8 | F13: =IF(OR(C13="",D13="",C13=0),"",(D13-C13)/C13) | H13: =IF(F13="","",IF(F13=0,"Sin desviación",IF(G13="Sí","Mayor","Menor")))
A14: 9 | F14: =IF(OR(C14="",D14="",C14=0),"",(D14-C14)/C14) | H14: =IF(F14="","",IF(F14=0,"Sin desviación",IF(G14="Sí","Mayor","Menor")))
A15: 10 | F15: =IF(OR(C15="",D15="",C15=0),"",(D15-C15)/C15) | H15: =IF(F15="","",IF(F15=0,"Sin desviación",IF(G15="Sí","Mayor","Menor")))
B17: Desviaciones mayores | C17: =COUNTIF(H6:H15,"Mayor") -> 0
B18: Desviaciones menores | C18: =COUNTIF(H6:H15,"Menor") -> 0
A20: Mayor: afecta dosis, participantes o medición → acción correctiva, aviso al asesor y reporte en limitaciones. Menor: se corrige y registra.

Sheet 6_Control_Cambios
A1: REGISTRO DE CONTROL DE CAMBIOS
A2: Seminario de Tesis III – Sesión 6: Monitoreo, fidelidad y control de incidencias | Celdas amarillas con texto azul = datos que ingresa el tesista; celdas blancas = fórmulas (no modificar)
A4: Código | B4: Fecha | C4: Elemento modificado | D4: Versión / condición anterior | E4: Versión / condición nueva | F4: Motivo | G4: INC relacionada | H4: Aprobado por | I4: Fecha de aprobación | J4: Impacto esperado en la VD | K4: Evidencia
A21: Celdas de aprobación resaltadas en ámbar = cambio sin aprobación documentada (resolver antes del postest).

Sheet 7_Rubrica
A1: INSTRUMENTO 5: RÚBRICA DEL INFORME DE SEGUIMIENTO
A2: Seminario de Tesis III – Sesión 6: Monitoreo, fidelidad y control de incidencias | Celdas amarillas con texto azul = datos que ingresa el tesista; celdas blancas = fórmulas (no modificar)
A4: Criterio | B4: Eficiente (5) | C4: Regular (3) | D4: Deficiente (0) | E4: Autoevaluación | F4: Evaluación docente | G4: Retroalimentación
A5: Registros de monitoreo | B5: Completos, semanales y con evidencias | C5: Incompletos o sin evidencias | D5: Inexistentes
A6: Fidelidad de la intervención | B6: IF calculado por dimensión y semana | C6: IF global sin detalle | D6: No se evalúa
A7: Incidencias | B7: Codificadas, clasificadas y cerradas | C7: Registradas sin clasificar | D7: No se registran
A8: Variables intervinientes | B8: Matriz con control y evidencia | C8: Listadas sin control | D8: No identificadas
A9: Acciones correctivas y cambios | B9: Verificadas y aprobadas | C9: Sin verificación | D9: Cambios no documentados
A10: Trazabilidad y redacción | B10: Códigos cruzados y APA 7 | C10: Trazabilidad parcial | D10: Sin trazabilidad
A11: PUNTAJE (máx. 30) | E11: =SUM(E5:E10) -> 0 | F11: =SUM(F5:F10) -> 0
A12: NOTA VIGESIMAL (0–20) | E12: =ROUND(E11/30*20,1) -> 0 | F12: =IF(COUNT(F5:F10)=0,"",ROUND(F11/30*20,1))
A14: La nota vigesimal se integra al Promedio de Tareas Académicas (PTA). NF = (PTA + EMC + EF) / 3.

Sheet 8_Resumen
A1: TABLERO RESUMEN DEL MONITOREO
A2: Se actualiza automáticamente con las hojas 1 a 7. Úselo como base de la sección de resultados del informe de seguimiento.
A4: Indicador | B4: Valor | D4: Severidad | E4: N.° incidencias
A5: Tesista | B5: =Instrucciones!C5 -> Trujillo Avila, Marcel Alexander Javier; Godoy Condezo, Alejandro Jeanpier | D5: Crítica | E5: =COUNTIF('2_Registro_Incidencias'!J5:J34,D5) -> 0
A6: Diseño | B6: =Instrucciones!C10 -> Preexperimental: G O1 X O2 | D6: Alta | E6: =COUNTIF('2_Registro_Incidencias'!J5:J34,D6) -> 0
A7: IF semanal promedio (hoja 1) | B7: ='1_Ficha_Monitoreo'!Q18 | D7: Media | E7: =COUNTIF('2_Registro_Incidencias'!J5:J34,D7) -> 0
A8: Nivel (hoja 1) | B8: ='1_Ficha_Monitoreo'!R18 | D8: Baja | E8: =COUNTIF('2_Registro_Incidencias'!J5:J34,D8) -> 0
A9: IF global lista de cotejo (hoja 3) | B9: ='3_Cotejo_Fidelidad'!C18
A10: Nivel (hoja 3) | B10: ='3_Cotejo_Fidelidad'!C19 | D10: Tipo | E10: N.° incidencias
A11: Disponibilidad global del sistema | B11: ='1_Ficha_Monitoreo'!G18 | D11: Técnica | E11: =COUNTIF('2_Registro_Incidencias'!G5:G34,D11) -> 0
A12: Exposición global (transacciones) | B12: ='1_Ficha_Monitoreo'!M18 | D12: Metodológica | E12: =COUNTIF('2_Registro_Incidencias'!G5:G34,D12) -> 0
A13: Participación promedio | B13: ='1_Ficha_Monitoreo'!J18
A14: Participantes iniciales | B14: ='1_Ficha_Monitoreo'!H6 -> 108
A15: Participantes finales (última semana registrada) | B15: =LOOKUP(2,1/('1_Ficha_Monitoreo'!H6:H17<>""),'1_Ficha_Monitoreo'!H6:H17) -> #N/A
A16: Mortalidad experimental | B16: =IF(B14=0,"",(B14-B15)/B14) -> #N/A
A17: Total de incidencias | B17: =COUNTA('2_Registro_Incidencias'!F5:F34) -> 0
A18: Incidencias abiertas o en curso | B18: =COUNTIF('2_Registro_Incidencias'!Q5:Q34,"Abierta")+COUNTIF('2_Registro_Incidencias'!Q5:Q34,"En curso") -> 0
A19: Desviaciones mayores | B19: ='5_Desviaciones'!C17 -> 0
A20: Cambios registrados | B20: =COUNTA('6_Control_Cambios'!A5:A19) -> 0
A21: Variables de riesgo alto | B21: =COUNTIF('4_Matriz_Variables'!G5:G16,"Alto") -> 3
A22: Nota del informe (autoevaluación) | B22: ='7_Rubrica'!E12 -> 0

Sheet Listas
A1: Tipo_incidencia | B1: Nivel | C1: Estado | D1: Amenaza | E1: Tipo_variable | F1: SiNo | G1: Puntaje | H1: Grupo | I1: Estado_control | K1: Matriz de prioridad (ITIL 4, adaptada)
A2: Técnica | B2: Alta | C2: Abierta | D2: Ninguna | E2: Del participante | F2: Sí | G2: 5 | H2: GE | I2: Controlada | K2: Impacto \ Urgencia | L2: Alta | M2: Media | N2: Baja
A3: Metodológica | B3: Media | C3: En curso | D3: Historia | E3: Organizacional | F3: No | G3: 3 | H3: GC | I3: Parcialmente controlada | K3: Alta | L3: Crítica | M3: Alta | N3: Media
B4: Baja | C4: Cerrada | D4: Maduración | E4: Tecnológica | G4: 0 | H4: Único (preexperimental) | I4: No controlada | K4: Media | L4: Alta | M4: Media | N4: Baja
D5: Administración de pruebas | E5: Del investigador | K5: Baja | L5: Media | M5: Baja | N5: Baja
D6: Instrumentación | E6: Externa / temporal
D7: Regresión estadística
D8: Selección
D9: Mortalidad experimental
D10: Difusión / contaminación
D11: Dosis baja (fidelidad)
